{"code": "", "data": {"count": 2, "anchorStr": "959782996528029696", "records": [{"comment": "#Road rage much ? \ud83d\ude09", "userId": 958715497929687040, "postIdStr": "959521456600068096", "flags|platform_hi": 0, "vanityUrls": [], "verified": 0, "twitterVerified": 0, "avatarUrl": "http://v.cdn.vine.co/v/avatars/AED86EB2-1DA4-4A73-A4C9-841E3D60582A-17200-000001DDDAE11004bd92cdd3ad.jpg?versionId=2x4.bK2l.iN4qUiuzhfshWSQx96zlcyp", "entities": [{"title": "Road", "idStr": "906320583518859264", "range": [0, 5], "link": "vine://tag/road", "type": "tag", "id": 906320583518859264}], "location": null, "commentId": 959782996528029696, "username": "emeryMUSIC4life", "userIdStr": "958715497929687040", "sourceType": null, "commentIdStr": "959782996528029696", "user": {"username": "emeryMUSIC4life", "twitterScreenname": "lovemery67", "userIdStr": "958715497929687040", "verified": 0, "vanityUrls": [], "twitterVerified": 0, "avatarUrl": "http://v.cdn.vine.co/v/avatars/AED86EB2-1DA4-4A73-A4C9-841E3D60582A-17200-000001DDDAE11004bd92cdd3ad.jpg?versionId=2x4.bK2l.iN4qUiuzhfshWSQx96zlcyp", "userId": 958715497929687040, "private": 0, "location": null, "description": "Muisc is life."}, "postId": 959521456600068096, "twitterScreenname": "lovemery67", "created": "2013-06-21T08:45:12.000000", "sourceId": null, "flags|platform_lo": 0, "sourceIdStr": ""}, {"comment": "#Road rage much ? \ud83d\ude09", "userId": 958715497929687040, "postIdStr": "959521456600068096", "flags|platform_hi": 0, "vanityUrls": [], "verified": 0, "twitterVerified": 0, "avatarUrl": "http://v.cdn.vine.co/v/avatars/AED86EB2-1DA4-4A73-A4C9-841E3D60582A-17200-000001DDDAE11004bd92cdd3ad.jpg?versionId=2x4.bK2l.iN4qUiuzhfshWSQx96zlcyp", "entities": [{"title": "Road", "idStr": "906320583518859264", "range": [0, 5], "link": "vine://tag/road", "type": "tag", "id": 906320583518859264}], "location": null, "commentId": 959783117617582080, "username": "emeryMUSIC4life", "userIdStr": "958715497929687040", "sourceType": null, "commentIdStr": "959783117617582080", "user": {"username": "emeryMUSIC4life", "twitterScreenname": "lovemery67", "userIdStr": "958715497929687040", "verified": 0, "vanityUrls": [], "twitterVerified": 0, "avatarUrl": "http://v.cdn.vine.co/v/avatars/AED86EB2-1DA4-4A73-A4C9-841E3D60582A-17200-000001DDDAE11004bd92cdd3ad.jpg?versionId=2x4.bK2l.iN4qUiuzhfshWSQx96zlcyp", "userId": 958715497929687040, "private": 0, "location": null, "description": "Muisc is life."}, "postId": 959521456600068096, "twitterScreenname": "lovemery67", "created": "2013-06-21T08:45:41.000000", "sourceId": null, "flags|platform_lo": 0, "sourceIdStr": ""}], "nextPage": null, "backAnchor": "", "anchor": 959782996528029696, "previousPage": null, "size": 100}, "success": true, "error": ""}