{"code": "", "data": {"count": 13, "anchorStr": "966080513259491328", "records": [{"comment": "Lmao. You just HAD to one up me didn't you", "userId": 944317825038827520, "postIdStr": "966080360632946688", "flags|platform_hi": 0, "vanityUrls": ["GabrielleXavier"], "verified": 0, "twitterVerified": 0, "avatarUrl": "http://v.cdn.vine.co/r/avatars/E78EFBB11C991620144424009728_1043ba01038.3.2_NWROKI7OSB_Ed6XG99dhdiuRpGc3lpOqKo2XNAP92stmVW48PXix32hdfUIEOPsh.jpg?versionId=MOQ.miT1GLOIS58xZ6ujSC0ZP1vMankh", "entities": [], "location": "Toronto", "commentId": 966080513259491328, "username": "Gabrielle Xavier", "userIdStr": "944317825038827520", "sourceType": null, "commentIdStr": "966080513259491328", "user": {"username": "Gabrielle Xavier", "twitterScreenname": "xoxGabrielle", "userIdStr": "944317825038827520", "verified": 0, "vanityUrls": ["GabrielleXavier"], "twitterVerified": 0, "avatarUrl": "http://v.cdn.vine.co/r/avatars/E78EFBB11C991620144424009728_1043ba01038.3.2_NWROKI7OSB_Ed6XG99dhdiuRpGc3lpOqKo2XNAP92stmVW48PXix32hdfUIEOPsh.jpg?versionId=MOQ.miT1GLOIS58xZ6ujSC0ZP1vMankh", "userId": 944317825038827520, "profileBackground": "0x5082e5", "private": 0, "location": "Toronto", "description": "Twitter - xoxgabrielle                                   Instagram - gabriellexavier"}, "postId": 966080360632946688, "twitterScreenname": "xoxGabrielle", "created": "2013-07-08T17:49:17.000000", "sourceId": null, "flags|platform_lo": 0, "sourceIdStr": ""}, {"comment": "Are you using your remote as a phone", "userId": 944317825038827520, "postIdStr": "966080360632946688", "flags|platform_hi": 0, "vanityUrls": ["GabrielleXavier"], "verified": 0, "twitterVerified": 0, "avatarUrl": "http://v.cdn.vine.co/r/avatars/E78EFBB11C991620144424009728_1043ba01038.3.2_NWROKI7OSB_Ed6XG99dhdiuRpGc3lpOqKo2XNAP92stmVW48PXix32hdfUIEOPsh.jpg?versionId=MOQ.miT1GLOIS58xZ6ujSC0ZP1vMankh", "entities": [], "location": "Toronto", "commentId": 966081524636233728, "username": "Gabrielle Xavier", "userIdStr": "944317825038827520", "sourceType": null, "commentIdStr": "966081524636233728", "user": {"username": "Gabrielle Xavier", "twitterScreenname": "xoxGabrielle", "userIdStr": "944317825038827520", "verified": 0, "vanityUrls": ["GabrielleXavier"], "twitterVerified": 0, "avatarUrl": "http://v.cdn.vine.co/r/avatars/E78EFBB11C991620144424009728_1043ba01038.3.2_NWROKI7OSB_Ed6XG99dhdiuRpGc3lpOqKo2XNAP92stmVW48PXix32hdfUIEOPsh.jpg?versionId=MOQ.miT1GLOIS58xZ6ujSC0ZP1vMankh", "userId": 944317825038827520, "profileBackground": "0x5082e5", "private": 0, "location": "Toronto", "description": "Twitter - xoxgabrielle                                   Instagram - gabriellexavier"}, "postId": 966080360632946688, "twitterScreenname": "xoxGabrielle", "created": "2013-07-08T17:53:18.000000", "sourceId": null, "flags|platform_lo": 0, "sourceIdStr": ""}, {"comment": "Gabrielle Xavier maybe. Yes.. \ud83d\ude0e", "userId": 937490693683855360, "postIdStr": "966080360632946688", "flags|platform_hi": 0, "vanityUrls": ["Atticus.White"], "verified": 0, "twitterVerified": 0, "avatarUrl": "http://v.cdn.vine.co/r/avatars/46CD896A87976325347794919424_1da5e46134d.3.1_roOZjCGTKsxQqZkatx46F9VNQgWc.UcZnpa2xDI2czPxcbYw.BDBzLLGJit72hio.jpg?versionId=x2heTNPRe6keJSgp_d5mH3puqzYWASHK", "entities": [{"vanityUrls": ["GabrielleXavier"], "title": "Gabrielle Xavier", "idStr": "944317825038827520", "range": [0, 16], "link": "vine://user-id/944317825038827520", "type": "mention", "id": 944317825038827520}], "location": "Boston", "commentId": 966082321944039424, "username": "Atticus White", "userIdStr": "937490693683855360", "sourceType": null, "commentIdStr": "966082321944039424", "user": {"username": "Atticus White", "twitterScreenname": "atticoos", "userIdStr": "937490693683855360", "verified": 0, "vanityUrls": ["Atticus.White"], "twitterVerified": 0, "avatarUrl": "http://v.cdn.vine.co/r/avatars/46CD896A87976325347794919424_1da5e46134d.3.1_roOZjCGTKsxQqZkatx46F9VNQgWc.UcZnpa2xDI2czPxcbYw.BDBzLLGJit72hio.jpg?versionId=x2heTNPRe6keJSgp_d5mH3puqzYWASHK", "userId": 937490693683855360, "private": 0, "location": "Boston", "description": "In real life I'm a programmer, here I am not. twitter:ajwhite89"}, "postId": 966080360632946688, "twitterScreenname": "atticoos", "created": "2013-07-08T17:56:28.000000", "sourceId": null, "flags|platform_lo": 0, "sourceIdStr": ""}, {"comment": "Atticus White Your Soo Funny \ud83d\ude02\ud83d\udc4c", "userId": 949183624585056256, "postIdStr": "966080360632946688", "flags|platform_hi": 0, "vanityUrls": [], "verified": 0, "twitterVerified": 0, "avatarUrl": "http://v.cdn.vine.co/r/avatars/6A4E6F51EB1359031817809899520_5e79c92f031.25.1.jpg?versionId=deqwTAAJFS3lY76CIIcC_jZGVmaEeruG", "entities": [{"vanityUrls": ["Atticus.White"], "title": "Atticus White", "idStr": "937490693683855360", "range": [0, 13], "link": "vine://user-id/937490693683855360", "type": "mention", "id": 937490693683855360}], "location": "Jesus  \ud83d\ude0e\ud83d\ude4c", "commentId": 966087032407474176, "username": "Luan Moreira", "userIdStr": "949183624585056256", "sourceType": null, "commentIdStr": "966087032407474176", "user": {"username": "Luan Moreira", "twitterScreenname": "Luanepicdino", "userIdStr": "949183624585056256", "verified": 0, "vanityUrls": [], "twitterVerified": 0, "avatarUrl": "http://v.cdn.vine.co/r/avatars/6A4E6F51EB1359031817809899520_5e79c92f031.25.1.jpg?versionId=deqwTAAJFS3lY76CIIcC_jZGVmaEeruG", "userId": 949183624585056256, "profileBackground": "0x33ccbf", "private": 0, "location": "Jesus  \ud83d\ude0e\ud83d\ude4c", "description": "\ud83d\ude0f"}, "postId": 966080360632946688, "twitterScreenname": "Luanepicdino", "created": "2013-07-08T18:15:11.000000", "sourceId": null, "flags|platform_lo": 0, "sourceIdStr": ""}, {"comment": "Lol! One up'd indeed jaja", "userId": 948744904752955392, "postIdStr": "966080360632946688", "flags|platform_hi": 0, "vanityUrls": [], "verified": 0, "twitterVerified": 0, "avatarUrl": "http://v.cdn.vine.co/v/avatars/5CB6F0F6-4FB1-4908-AB98-3A29D10F4D24-542-000000582F0B4CE7.jpg?versionId=.cGjZSabXSvrX90IS5uKLzXUo7iRqz99", "entities": [], "location": "Chicago", "commentId": 966173284641218560, "username": "Jonatan Viveros", "userIdStr": "948744904752955392", "sourceType": null, "commentIdStr": "966173284641218560", "user": {"username": "Jonatan Viveros", "twitterScreenname": "Prophesy_SoM", "userIdStr": "948744904752955392", "verified": 0, "vanityUrls": [], "twitterVerified": 0, "avatarUrl": "http://v.cdn.vine.co/v/avatars/5CB6F0F6-4FB1-4908-AB98-3A29D10F4D24-542-000000582F0B4CE7.jpg?versionId=.cGjZSabXSvrX90IS5uKLzXUo7iRqz99", "userId": 948744904752955392, "profileBackground": "0x68bf60", "private": 0, "location": "Chicago", "description": "Christian. Charismatic. Calvinist."}, "postId": 966080360632946688, "twitterScreenname": "Prophesy_SoM", "created": "2013-07-08T23:57:55.000000", "sourceId": null, "flags|platform_lo": 0, "sourceIdStr": ""}, {"comment": "Pfft Jonatan Viveros", "userId": 944317825038827520, "postIdStr": "966080360632946688", "flags|platform_hi": 0, "vanityUrls": ["GabrielleXavier"], "verified": 0, "twitterVerified": 0, "avatarUrl": "http://v.cdn.vine.co/r/avatars/E78EFBB11C991620144424009728_1043ba01038.3.2_NWROKI7OSB_Ed6XG99dhdiuRpGc3lpOqKo2XNAP92stmVW48PXix32hdfUIEOPsh.jpg?versionId=MOQ.miT1GLOIS58xZ6ujSC0ZP1vMankh", "entities": [{"vanityUrls": [], "title": "Jonatan Viveros", "idStr": "948744904752955392", "range": [5, 20], "link": "vine://user-id/948744904752955392", "type": "mention", "id": 948744904752955392}], "location": "Toronto", "commentId": 966173794169417728, "username": "Gabrielle Xavier", "userIdStr": "944317825038827520", "sourceType": null, "commentIdStr": "966173794169417728", "user": {"username": "Gabrielle Xavier", "twitterScreenname": "xoxGabrielle", "userIdStr": "944317825038827520", "verified": 0, "vanityUrls": ["GabrielleXavier"], "twitterVerified": 0, "avatarUrl": "http://v.cdn.vine.co/r/avatars/E78EFBB11C991620144424009728_1043ba01038.3.2_NWROKI7OSB_Ed6XG99dhdiuRpGc3lpOqKo2XNAP92stmVW48PXix32hdfUIEOPsh.jpg?versionId=MOQ.miT1GLOIS58xZ6ujSC0ZP1vMankh", "userId": 944317825038827520, "profileBackground": "0x5082e5", "private": 0, "location": "Toronto", "description": "Twitter - xoxgabrielle                                   Instagram - gabriellexavier"}, "postId": 966080360632946688, "twitterScreenname": "xoxGabrielle", "created": "2013-07-08T23:59:57.000000", "sourceId": null, "flags|platform_lo": 0, "sourceIdStr": ""}, {"comment": "Lmao to the remote I was like wtf is that. Gabrielle Xavier", "username": "Brittany", "userIdStr": "957563207831212032", "verified": 0, "vanityUrls": [], "twitterVerified": 0, "flags|platform_lo": 0, "sourceId": null, "commentIdStr": "966396514027323392", "avatarUrl": "http://v.cdn.vine.co/v/avatars/A28E1B89-2883-45F4-B993-CAEF04A47C97-2105-000000F5A6C0C4521f97ef632e.jpg?versionId=ZdbcOh0u6.Cap3aYmN2Ul3adCivI_Y1o", "userId": 957563207831212032, "created": "2013-07-09T14:44:57.000000", "entities": [{"vanityUrls": ["GabrielleXavier"], "title": "Gabrielle Xavier", "idStr": "944317825038827520", "range": [43, 59], "link": "vine://user-id/944317825038827520", "type": "mention", "id": 944317825038827520}], "postIdStr": "966080360632946688", "user": {"username": "Brittany", "userIdStr": "957563207831212032", "verified": 0, "vanityUrls": [], "twitterVerified": 0, "avatarUrl": "http://v.cdn.vine.co/v/avatars/A28E1B89-2883-45F4-B993-CAEF04A47C97-2105-000000F5A6C0C4521f97ef632e.jpg?versionId=ZdbcOh0u6.Cap3aYmN2Ul3adCivI_Y1o", "userId": 957563207831212032, "private": 0, "location": null, "description": ""}, "commentId": 966396514027323392, "sourceType": null, "postId": 966080360632946688, "flags|platform_hi": 0, "sourceIdStr": "", "location": null}, {"comment": "Yah he's special Brittany", "userId": 944317825038827520, "postIdStr": "966080360632946688", "flags|platform_hi": 0, "vanityUrls": ["GabrielleXavier"], "verified": 0, "twitterVerified": 0, "avatarUrl": "http://v.cdn.vine.co/r/avatars/E78EFBB11C991620144424009728_1043ba01038.3.2_NWROKI7OSB_Ed6XG99dhdiuRpGc3lpOqKo2XNAP92stmVW48PXix32hdfUIEOPsh.jpg?versionId=MOQ.miT1GLOIS58xZ6ujSC0ZP1vMankh", "entities": [{"vanityUrls": [], "title": "Brittany", "idStr": "957563207831212032", "range": [17, 25], "link": "vine://user-id/957563207831212032", "type": "mention", "id": 957563207831212032}], "location": "Toronto", "commentId": 966396772337520640, "username": "Gabrielle Xavier", "userIdStr": "944317825038827520", "sourceType": null, "commentIdStr": "966396772337520640", "user": {"username": "Gabrielle Xavier", "twitterScreenname": "xoxGabrielle", "userIdStr": "944317825038827520", "verified": 0, "vanityUrls": ["GabrielleXavier"], "twitterVerified": 0, "avatarUrl": "http://v.cdn.vine.co/r/avatars/E78EFBB11C991620144424009728_1043ba01038.3.2_NWROKI7OSB_Ed6XG99dhdiuRpGc3lpOqKo2XNAP92stmVW48PXix32hdfUIEOPsh.jpg?versionId=MOQ.miT1GLOIS58xZ6ujSC0ZP1vMankh", "userId": 944317825038827520, "profileBackground": "0x5082e5", "private": 0, "location": "Toronto", "description": "Twitter - xoxgabrielle                                   Instagram - gabriellexavier"}, "postId": 966080360632946688, "twitterScreenname": "xoxGabrielle", "created": "2013-07-09T14:45:59.000000", "sourceId": null, "flags|platform_lo": 0, "sourceIdStr": ""}, {"comment": "Brittany, Gabrielle Xavier using a remote was like.. The whole point of this joke \ud83d\ude10...\ud83d\ude11...\ud83d\ude10", "userId": 937490693683855360, "postIdStr": "966080360632946688", "flags|platform_hi": 0, "vanityUrls": ["Atticus.White"], "verified": 0, "twitterVerified": 0, "avatarUrl": "http://v.cdn.vine.co/r/avatars/46CD896A87976325347794919424_1da5e46134d.3.1_roOZjCGTKsxQqZkatx46F9VNQgWc.UcZnpa2xDI2czPxcbYw.BDBzLLGJit72hio.jpg?versionId=x2heTNPRe6keJSgp_d5mH3puqzYWASHK", "entities": [{"vanityUrls": [], "title": "Brittany", "idStr": "957563207831212032", "range": [0, 8], "link": "vine://user-id/957563207831212032", "type": "mention", "id": 957563207831212032}, {"vanityUrls": ["GabrielleXavier"], "title": "Gabrielle Xavier", "idStr": "944317825038827520", "range": [10, 26], "link": "vine://user-id/944317825038827520", "type": "mention", "id": 944317825038827520}], "location": "Boston", "commentId": 966407472728416256, "username": "Atticus White", "userIdStr": "937490693683855360", "sourceType": null, "commentIdStr": "966407472728416256", "user": {"username": "Atticus White", "twitterScreenname": "atticoos", "userIdStr": "937490693683855360", "verified": 0, "vanityUrls": ["Atticus.White"], "twitterVerified": 0, "avatarUrl": "http://v.cdn.vine.co/r/avatars/46CD896A87976325347794919424_1da5e46134d.3.1_roOZjCGTKsxQqZkatx46F9VNQgWc.UcZnpa2xDI2czPxcbYw.BDBzLLGJit72hio.jpg?versionId=x2heTNPRe6keJSgp_d5mH3puqzYWASHK", "userId": 937490693683855360, "private": 0, "location": "Boston", "description": "In real life I'm a programmer, here I am not. twitter:ajwhite89"}, "postId": 966080360632946688, "twitterScreenname": "atticoos", "created": "2013-07-09T15:28:30.000000", "sourceId": null, "flags|platform_lo": 0, "sourceIdStr": ""}, {"comment": "Lol totally", "userId": 944317825038827520, "postIdStr": "966080360632946688", "flags|platform_hi": 0, "vanityUrls": ["GabrielleXavier"], "verified": 0, "twitterVerified": 0, "avatarUrl": "http://v.cdn.vine.co/r/avatars/E78EFBB11C991620144424009728_1043ba01038.3.2_NWROKI7OSB_Ed6XG99dhdiuRpGc3lpOqKo2XNAP92stmVW48PXix32hdfUIEOPsh.jpg?versionId=MOQ.miT1GLOIS58xZ6ujSC0ZP1vMankh", "entities": [], "location": "Toronto", "commentId": 966409931589025792, "username": "Gabrielle Xavier", "userIdStr": "944317825038827520", "sourceType": null, "commentIdStr": "966409931589025792", "user": {"username": "Gabrielle Xavier", "twitterScreenname": "xoxGabrielle", "userIdStr": "944317825038827520", "verified": 0, "vanityUrls": ["GabrielleXavier"], "twitterVerified": 0, "avatarUrl": "http://v.cdn.vine.co/r/avatars/E78EFBB11C991620144424009728_1043ba01038.3.2_NWROKI7OSB_Ed6XG99dhdiuRpGc3lpOqKo2XNAP92stmVW48PXix32hdfUIEOPsh.jpg?versionId=MOQ.miT1GLOIS58xZ6ujSC0ZP1vMankh", "userId": 944317825038827520, "profileBackground": "0x5082e5", "private": 0, "location": "Toronto", "description": "Twitter - xoxgabrielle                                   Instagram - gabriellexavier"}, "postId": 966080360632946688, "twitterScreenname": "xoxGabrielle", "created": "2013-07-09T15:38:16.000000", "sourceId": null, "flags|platform_lo": 0, "sourceIdStr": ""}, {"comment": "\ud83d\ude09\ud83d\ude18", "userId": 937490693683855360, "postIdStr": "966080360632946688", "flags|platform_hi": 0, "vanityUrls": ["Atticus.White"], "verified": 0, "twitterVerified": 0, "avatarUrl": "http://v.cdn.vine.co/r/avatars/46CD896A87976325347794919424_1da5e46134d.3.1_roOZjCGTKsxQqZkatx46F9VNQgWc.UcZnpa2xDI2czPxcbYw.BDBzLLGJit72hio.jpg?versionId=x2heTNPRe6keJSgp_d5mH3puqzYWASHK", "entities": [], "location": "Boston", "commentId": 966410950968479744, "username": "Atticus White", "userIdStr": "937490693683855360", "sourceType": null, "commentIdStr": "966410950968479744", "user": {"username": "Atticus White", "twitterScreenname": "atticoos", "userIdStr": "937490693683855360", "verified": 0, "vanityUrls": ["Atticus.White"], "twitterVerified": 0, "avatarUrl": "http://v.cdn.vine.co/r/avatars/46CD896A87976325347794919424_1da5e46134d.3.1_roOZjCGTKsxQqZkatx46F9VNQgWc.UcZnpa2xDI2czPxcbYw.BDBzLLGJit72hio.jpg?versionId=x2heTNPRe6keJSgp_d5mH3puqzYWASHK", "userId": 937490693683855360, "private": 0, "location": "Boston", "description": "In real life I'm a programmer, here I am not. twitter:ajwhite89"}, "postId": 966080360632946688, "twitterScreenname": "atticoos", "created": "2013-07-09T15:42:19.000000", "sourceId": null, "flags|platform_lo": 0, "sourceIdStr": ""}, {"comment": "Gabrielle Xavier I think he just kissed at me \ud83d\ude33", "username": "Brittany", "userIdStr": "957563207831212032", "verified": 0, "vanityUrls": [], "twitterVerified": 0, "flags|platform_lo": 0, "sourceId": null, "commentIdStr": "967215769828192256", "avatarUrl": "http://v.cdn.vine.co/v/avatars/A28E1B89-2883-45F4-B993-CAEF04A47C97-2105-000000F5A6C0C4521f97ef632e.jpg?versionId=ZdbcOh0u6.Cap3aYmN2Ul3adCivI_Y1o", "userId": 957563207831212032, "created": "2013-07-11T21:00:23.000000", "entities": [{"vanityUrls": ["GabrielleXavier"], "title": "Gabrielle Xavier", "idStr": "944317825038827520", "range": [0, 16], "link": "vine://user-id/944317825038827520", "type": "mention", "id": 944317825038827520}], "postIdStr": "966080360632946688", "user": {"username": "Brittany", "userIdStr": "957563207831212032", "verified": 0, "vanityUrls": [], "twitterVerified": 0, "avatarUrl": "http://v.cdn.vine.co/v/avatars/A28E1B89-2883-45F4-B993-CAEF04A47C97-2105-000000F5A6C0C4521f97ef632e.jpg?versionId=ZdbcOh0u6.Cap3aYmN2Ul3adCivI_Y1o", "userId": 957563207831212032, "private": 0, "location": null, "description": ""}, "commentId": 967215769828192256, "sourceType": null, "postId": 966080360632946688, "flags|platform_hi": 0, "sourceIdStr": "", "location": null}, {"comment": "Yah he doesn't really understand boundaries Brittany", "userId": 944317825038827520, "postIdStr": "966080360632946688", "flags|platform_hi": 0, "vanityUrls": ["GabrielleXavier"], "verified": 0, "twitterVerified": 0, "avatarUrl": "http://v.cdn.vine.co/r/avatars/E78EFBB11C991620144424009728_1043ba01038.3.2_NWROKI7OSB_Ed6XG99dhdiuRpGc3lpOqKo2XNAP92stmVW48PXix32hdfUIEOPsh.jpg?versionId=MOQ.miT1GLOIS58xZ6ujSC0ZP1vMankh", "entities": [{"vanityUrls": [], "title": "Brittany", "idStr": "957563207831212032", "range": [44, 52], "link": "vine://user-id/957563207831212032", "type": "mention", "id": 957563207831212032}], "location": "Toronto", "commentId": 967215904926871552, "username": "Gabrielle Xavier", "userIdStr": "944317825038827520", "sourceType": null, "commentIdStr": "967215904926871552", "user": {"username": "Gabrielle Xavier", "twitterScreenname": "xoxGabrielle", "userIdStr": "944317825038827520", "verified": 0, "vanityUrls": ["GabrielleXavier"], "twitterVerified": 0, "avatarUrl": "http://v.cdn.vine.co/r/avatars/E78EFBB11C991620144424009728_1043ba01038.3.2_NWROKI7OSB_Ed6XG99dhdiuRpGc3lpOqKo2XNAP92stmVW48PXix32hdfUIEOPsh.jpg?versionId=MOQ.miT1GLOIS58xZ6ujSC0ZP1vMankh", "userId": 944317825038827520, "profileBackground": "0x5082e5", "private": 0, "location": "Toronto", "description": "Twitter - xoxgabrielle                                   Instagram - gabriellexavier"}, "postId": 966080360632946688, "twitterScreenname": "xoxGabrielle", "created": "2013-07-11T21:00:55.000000", "sourceId": null, "flags|platform_lo": 0, "sourceIdStr": ""}], "nextPage": null, "backAnchor": "", "anchor": 966080513259491328, "previousPage": null, "size": 100}, "success": true, "error": ""}